chess_to_the_death/__init__.py
chess_to_the_death/__main__.py
chess_to_the_death/entity/__init__.py
chess_to_the_death/entity/pieces.py
chess_to_the_death/entity/player.py
chess_to_the_death/media/images/blackb.png
chess_to_the_death/media/images/blackk.png
chess_to_the_death/media/images/blackn.png
chess_to_the_death/media/images/blackp.png
chess_to_the_death/media/images/blackq.png
chess_to_the_death/media/images/blackr.png
chess_to_the_death/media/images/damage.png
chess_to_the_death/media/images/whiteb.png
chess_to_the_death/media/images/whitek.png
chess_to_the_death/media/images/whiten.png
chess_to_the_death/media/images/whitep.png
chess_to_the_death/media/images/whiteq.png
chess_to_the_death/media/images/whiter.png
chess_to_the_death/parser/__init__.py
chess_to_the_death/parser/argparser.py
chess_to_the_death/util/__init__.py
chess_to_the_death/util/action.py
chess_to_the_death/util/config.py
chess_to_the_death/util/definition.py
chess_to_the_death/util/engine.py
chess_to_the_death/util/fpsClock.py
chess_to_the_death/util/gui.py
chess_to_the_death/util/loader.py
chess_to_the_death/web/UpdateChecker.py
chess_to_the_death/web/__init__.py
chesstothedeath-0.1.2.dist-info/LICENSE
chesstothedeath-0.1.2.dist-info/WHEEL
chesstothedeath-0.1.2.dist-info/METADATA
chesstothedeath-0.1.2.dist-info/RECORD
