Metadata-Version: 2.1
Name: ChessToTheDeath
Version: 0.1.2
Summary: A simple chess variant where pieces have damage and health values.
Keywords: python,chess,pygame
Author-email: "Silas A. Kraume" <silas.kraume1552@gmail.com>
Requires-Python: >=3.7
Classifier: License :: OSI Approved :: MIT License
Classifier: Programming Language :: Python :: 3
Classifier: Operating System :: OS Independent
Requires-Dist: numpy>=1.22.0
Requires-Dist: pygame>=2.0.0
Project-URL: Download, https://github.com/SilenZcience/ChessToTheDeath/tarball/master
Project-URL: Github, https://github.com/SilenZcience/ChessToTheDeath
Project-URL: Tracker, https://github.com/SilenZcience/ChessToTheDeath/issues
